azure/__init__.py
azure/cli/__init__.py
azure/cli/command_modules/__init__.py
azure/cli/command_modules/privatedns/__init__.py
azure/cli/command_modules/privatedns/_client_factory.py
azure/cli/command_modules/privatedns/_format.py
azure/cli/command_modules/privatedns/_help.py
azure/cli/command_modules/privatedns/_params.py
azure/cli/command_modules/privatedns/_validators.py
azure/cli/command_modules/privatedns/commands.py
azure/cli/command_modules/privatedns/custom.py
opal_azure_cli_privatedns-1.0.4.dist-info/METADATA
opal_azure_cli_privatedns-1.0.4.dist-info/WHEEL
opal_azure_cli_privatedns-1.0.4.dist-info/top_level.txt
opal_azure_cli_privatedns-1.0.4.dist-info/RECORD
