Metadata-Version: 2.1
Name: opal-azure-cli-privatedns
Version: 1.0.4
Summary: Microsoft Azure Command-Line Tools Network PrivateDns Command Module
Home-page: https://github.com/Azure/azure-cli
Author: Microsoft Corporation
Author-email: azpycli@microsoft.com
License: MIT
Platform: UNKNOWN
Classifier: Development Status :: 5 - Production/Stable
Classifier: Intended Audience :: Developers
Classifier: Intended Audience :: System Administrators
Classifier: Programming Language :: Python
Classifier: Programming Language :: Python :: 2
Classifier: Programming Language :: Python :: 2.7
Classifier: Programming Language :: Python :: 3
Classifier: Programming Language :: Python :: 3.4
Classifier: Programming Language :: Python :: 3.5
Classifier: Programming Language :: Python :: 3.6
Classifier: License :: OSI Approved :: MIT License
Requires-Dist: azure-mgmt-network (==3.0.0)
Requires-Dist: azure-mgmt-privatedns (==0.1.0)
Requires-Dist: opal-azure-cli-core (>=2.0.68)
Requires-Dist: azure-cli-command-modules-nspkg (>=2.0.0)
